README.md
setup.py
deep-dostoewskiy/Untitled1.py
deep-dostoewskiy/Untitled2.py
deep-dostoewskiy/Untitled3.py
deep-dostoewskiy/__init__.py
deep-dostoewskiy/char-lstm-1.py
deep-dostoewskiy/char-lstm.py
deep-dostoewskiy/edward-vae.py
deep-dostoewskiy/get_samples.py
deep-dostoewskiy/hierarchy.py
deep-dostoewskiy/hierarchymagic.py
deep-dostoewskiy/keras-mnis.py
deep-dostoewskiy/manual_change-Copy1.py
deep-dostoewskiy/manual_change.py
deep-dostoewskiy/pretrained_word_embeddings.py
deep-dostoewskiy/scrape_from_libru.py
deep-dostoewskiy/vkozin97.py
hse-documents/__init__.py
hse-documents/filename.py
hse-documents/spider.py
ljpeg/__init__.py
ljpeg/ljpeg.py
sacred_nbextension.egg-info/PKG-INFO
sacred_nbextension.egg-info/SOURCES.txt
sacred_nbextension.egg-info/dependency_links.txt
sacred_nbextension.egg-info/top_level.txt
teacher_nbextension/__init__.py
teacher_nbextension/setup.py
teacher_nbextension/teacher_nbextension/__init__.py
teacher_nbextension/teacher_nbextension/handlers.py