Metadata-Version: 1.0
Name: sacred-nbextension
Version: 0.1.0
Summary: Amazing nbextension
Home-page: http://example.org
Author: John Doe
Author-email: UNKNOWN
License: UNKNOWN
Platform: UNKNOWN
